refractiveindex2/__init__.py
refractiveindex2/py.typed
refractiveindex2/refractiveindex.py
refractiveindex2-0.1.1.dist-info/licenses/LICENSE
refractiveindex2-0.1.1.dist-info/METADATA
refractiveindex2-0.1.1.dist-info/WHEEL
refractiveindex2-0.1.1.dist-info/top_level.txt
refractiveindex2-0.1.1.dist-info/RECORD
