Metadata-Version: 2.4
Name: refractiveindex2
Version: 0.1.1
Summary: A python interface to the refractiveindex.info database.
Author-email: Martin Schubert <mfschubert@gmail.com>
Maintainer-email: Martin Schubert <mfschubert@gmail.com>
License-Expression: MIT
Requires-Python: >=3.10
License-File: LICENSE
Requires-Dist: numpy
Requires-Dist: pyyaml
Requires-Dist: requests
Requires-Dist: types-PyYAML
Requires-Dist: types-requests
Provides-Extra: tests
Requires-Dist: parameterized; extra == "tests"
Requires-Dist: pytest; extra == "tests"
Requires-Dist: pytest-cov; extra == "tests"
Provides-Extra: dev
Requires-Dist: bump-my-version; extra == "dev"
Requires-Dist: darglint; extra == "dev"
Requires-Dist: isort; extra == "dev"
Requires-Dist: mypy; extra == "dev"
Requires-Dist: pre-commit; extra == "dev"
Dynamic: license-file
